{
  "ID": "317",
  "NAME": "опрос для создания фильтра",
  "TYPE": "опрос",
  "PAGES": 2,
  "QUESTION_COUNT": 12,
  "DATE_CREAT": "28.12.2023",
  "RESPONDENT": 7,
  "MIDDLE_TIME": {
    "MIN": 0,
    "SEC": 48
  },
  "UNFINISH": 0,
  "ACTIVE": true,
  "RESULTS": {
    "FORMS": {
      "90c21656-c81d-47f0-800a-44abfd799418": [
        [
          [
            {
              "ID": "449",
              "UF_ID_QUESTION": "1523",
              "UF_ID_FIELD": "1",
              "UF_ID_TYPE_FIELD": "text",
              "UF_VALUE_FIELD": "текст",
              "UF_FILED_ANSWER": "12312",
              "UF_FIELD_FILLED": "true"
            },
            {
              "ID": "450",
              "UF_ID_QUESTION": "1523",
              "UF_ID_FIELD": "60844eea-da56-4ea4-99c8-d943499f8a54",
              "UF_ID_TYPE_FIELD": "phone",
              "UF_VALUE_FIELD": "Телефон",
              "UF_FILED_ANSWER": "+7(123)123-12-31",
              "UF_FIELD_FILLED": "true"
            },
            {
              "ID": "451",
              "UF_ID_QUESTION": "1523",
              "UF_ID_FIELD": "8d734349-081f-4284-be52-e372e4c42ab4",
              "UF_ID_TYPE_FIELD": "email",
              "UF_VALUE_FIELD": "email",
              "UF_FILED_ANSWER": "фывфы@mail.ru",
              "UF_FIELD_FILLED": "true"
            },
            {
              "ID": "452",
              "UF_ID_QUESTION": "1523",
              "UF_ID_FIELD": "51a0cfc1-0241-4f67-9215-577227bbf25d",
              "UF_ID_TYPE_FIELD": "textarea",
              "UF_VALUE_FIELD": "Область текста",
              "UF_FILED_ANSWER": "фывфы@mail.ru",
              "UF_FIELD_FILLED": "true"
            }
          ]
        ],
        [
          [
            {
              "ID": "459",
              "UF_ID_QUESTION": "1535",
              "UF_ID_FIELD": "1",
              "UF_ID_TYPE_FIELD": "text",
              "UF_VALUE_FIELD": "текст",
              "UF_FILED_ANSWER": "123123",
              "UF_FIELD_FILLED": "true"
            },
            {
              "ID": "460",
              "UF_ID_QUESTION": "1535",
              "UF_ID_FIELD": "60844eea-da56-4ea4-99c8-d943499f8a54",
              "UF_ID_TYPE_FIELD": "phone",
              "UF_VALUE_FIELD": "Телефон",
              "UF_FILED_ANSWER": "+7(123)123-12-31",
              "UF_FIELD_FILLED": "true"
            },
            {
              "ID": "461",
              "UF_ID_QUESTION": "1535",
              "UF_ID_FIELD": "8d734349-081f-4284-be52-e372e4c42ab4",
              "UF_ID_TYPE_FIELD": "email",
              "UF_VALUE_FIELD": "email",
              "UF_FILED_ANSWER": "asdasd@mail.ru",
              "UF_FIELD_FILLED": "true"
            },
            {
              "ID": "462",
              "UF_ID_QUESTION": "1535",
              "UF_ID_FIELD": "51a0cfc1-0241-4f67-9215-577227bbf25d",
              "UF_ID_TYPE_FIELD": "textarea",
              "UF_VALUE_FIELD": "Область текста",
              "UF_FILED_ANSWER": "123123",
              "UF_FIELD_FILLED": "true"
            }
          ]
        ],
        [
          [
            {
              "ID": "469",
              "UF_ID_QUESTION": "1547",
              "UF_ID_FIELD": "1",
              "UF_ID_TYPE_FIELD": "text",
              "UF_VALUE_FIELD": "текст",
              "UF_FILED_ANSWER": "12312312",
              "UF_FIELD_FILLED": "true"
            },
            {
              "ID": "470",
              "UF_ID_QUESTION": "1547",
              "UF_ID_FIELD": "60844eea-da56-4ea4-99c8-d943499f8a54",
              "UF_ID_TYPE_FIELD": "phone",
              "UF_VALUE_FIELD": "Телефон",
              "UF_FILED_ANSWER": "+7(123)121-23-12",
              "UF_FIELD_FILLED": "true"
            },
            {
              "ID": "471",
              "UF_ID_QUESTION": "1547",
              "UF_ID_FIELD": "8d734349-081f-4284-be52-e372e4c42ab4",
              "UF_ID_TYPE_FIELD": "email",
              "UF_VALUE_FIELD": "email",
              "UF_FILED_ANSWER": "asds@mail.ru",
              "UF_FIELD_FILLED": "true"
            },
            {
              "ID": "472",
              "UF_ID_QUESTION": "1547",
              "UF_ID_FIELD": "51a0cfc1-0241-4f67-9215-577227bbf25d",
              "UF_ID_TYPE_FIELD": "textarea",
              "UF_VALUE_FIELD": "Область текста",
              "UF_FILED_ANSWER": "123123",
              "UF_FIELD_FILLED": "true"
            }
          ]
        ],
        [
          [
            {
              "ID": "479",
              "UF_ID_QUESTION": "1559",
              "UF_ID_FIELD": "1",
              "UF_ID_TYPE_FIELD": "text",
              "UF_VALUE_FIELD": "текст",
              "UF_FILED_ANSWER": "Поле имя",
              "UF_FIELD_FILLED": "true"
            },
            {
              "ID": "480",
              "UF_ID_QUESTION": "1559",
              "UF_ID_FIELD": "60844eea-da56-4ea4-99c8-d943499f8a54",
              "UF_ID_TYPE_FIELD": "phone",
              "UF_VALUE_FIELD": "Телефон",
              "UF_FILED_ANSWER": "+7(111)111-11-11",
              "UF_FIELD_FILLED": "true"
            },
            {
              "ID": "481",
              "UF_ID_QUESTION": "1559",
              "UF_ID_FIELD": "8d734349-081f-4284-be52-e372e4c42ab4",
              "UF_ID_TYPE_FIELD": "email",
              "UF_VALUE_FIELD": "email",
              "UF_FILED_ANSWER": "email@mail.ru",
              "UF_FIELD_FILLED": "true"
            },
            {
              "ID": "482",
              "UF_ID_QUESTION": "1559",
              "UF_ID_FIELD": "51a0cfc1-0241-4f67-9215-577227bbf25d",
              "UF_ID_TYPE_FIELD": "textarea",
              "UF_VALUE_FIELD": "Область текста",
              "UF_FILED_ANSWER": "Какой то текст",
              "UF_FIELD_FILLED": "true"
            }
          ]
        ],
        [
          [
            {
              "ID": "489",
              "UF_ID_QUESTION": "1571",
              "UF_ID_FIELD": "1",
              "UF_ID_TYPE_FIELD": "text",
              "UF_VALUE_FIELD": "текст",
              "UF_FILED_ANSWER": "123123",
              "UF_FIELD_FILLED": "true"
            },
            {
              "ID": "490",
              "UF_ID_QUESTION": "1571",
              "UF_ID_FIELD": "60844eea-da56-4ea4-99c8-d943499f8a54",
              "UF_ID_TYPE_FIELD": "phone",
              "UF_VALUE_FIELD": "Телефон",
              "UF_FILED_ANSWER": "+7(123)123-12-31",
              "UF_FIELD_FILLED": "true"
            },
            {
              "ID": "491",
              "UF_ID_QUESTION": "1571",
              "UF_ID_FIELD": "8d734349-081f-4284-be52-e372e4c42ab4",
              "UF_ID_TYPE_FIELD": "email",
              "UF_VALUE_FIELD": "email",
              "UF_FILED_ANSWER": "asdsa@mail.ru",
              "UF_FIELD_FILLED": "true"
            },
            {
              "ID": "492",
              "UF_ID_QUESTION": "1571",
              "UF_ID_FIELD": "51a0cfc1-0241-4f67-9215-577227bbf25d",
              "UF_ID_TYPE_FIELD": "textarea",
              "UF_VALUE_FIELD": "Область текста",
              "UF_FILED_ANSWER": "123123",
              "UF_FIELD_FILLED": "true"
            }
          ]
        ],
        [
          [
            {
              "ID": "499",
              "UF_ID_QUESTION": "1583",
              "UF_ID_FIELD": "1",
              "UF_ID_TYPE_FIELD": "text",
              "UF_VALUE_FIELD": "текст",
              "UF_FILED_ANSWER": "dfvasdf",
              "UF_FIELD_FILLED": "true"
            },
            {
              "ID": "500",
              "UF_ID_QUESTION": "1583",
              "UF_ID_FIELD": "60844eea-da56-4ea4-99c8-d943499f8a54",
              "UF_ID_TYPE_FIELD": "phone",
              "UF_VALUE_FIELD": "Телефон",
              "UF_FILED_ANSWER": "+7(123)121-23-12",
              "UF_FIELD_FILLED": "true"
            },
            {
              "ID": "501",
              "UF_ID_QUESTION": "1583",
              "UF_ID_FIELD": "8d734349-081f-4284-be52-e372e4c42ab4",
              "UF_ID_TYPE_FIELD": "email",
              "UF_VALUE_FIELD": "email",
              "UF_FILED_ANSWER": "asd@mail.ru",
              "UF_FIELD_FILLED": "true"
            },
            {
              "ID": "502",
              "UF_ID_QUESTION": "1583",
              "UF_ID_FIELD": "51a0cfc1-0241-4f67-9215-577227bbf25d",
              "UF_ID_TYPE_FIELD": "textarea",
              "UF_VALUE_FIELD": "Область текста",
              "UF_FILED_ANSWER": "asd@mail.ru",
              "UF_FIELD_FILLED": "true"
            }
          ]
        ],
        [
          [
            {
              "ID": "509",
              "UF_ID_QUESTION": "1595",
              "UF_ID_FIELD": "1",
              "UF_ID_TYPE_FIELD": "text",
              "UF_VALUE_FIELD": "текст",
              "UF_FILED_ANSWER": "Я текстовое поле",
              "UF_FIELD_FILLED": "true"
            },
            {
              "ID": "510",
              "UF_ID_QUESTION": "1595",
              "UF_ID_FIELD": "60844eea-da56-4ea4-99c8-d943499f8a54",
              "UF_ID_TYPE_FIELD": "phone",
              "UF_VALUE_FIELD": "Телефон",
              "UF_FILED_ANSWER": "+7(111)111-11-11",
              "UF_FIELD_FILLED": "true"
            },
            {
              "ID": "511",
              "UF_ID_QUESTION": "1595",
              "UF_ID_FIELD": "8d734349-081f-4284-be52-e372e4c42ab4",
              "UF_ID_TYPE_FIELD": "email",
              "UF_VALUE_FIELD": "email",
              "UF_FILED_ANSWER": "MYEmail@mail.ru",
              "UF_FIELD_FILLED": "true"
            },
            {
              "ID": "512",
              "UF_ID_QUESTION": "1595",
              "UF_ID_FIELD": "51a0cfc1-0241-4f67-9215-577227bbf25d",
              "UF_ID_TYPE_FIELD": "textarea",
              "UF_VALUE_FIELD": "Область текста",
              "UF_FILED_ANSWER": "Какой то рандомный текст",
              "UF_FIELD_FILLED": "true"
            }
          ]
        ]
      ],
      "0be8c1c0-7e08-46bc-929c-1d4f382ec74c": [
        [
          [
            {
              "ID": "453",
              "UF_ID_QUESTION": "1524",
              "UF_ID_FIELD": "1",
              "UF_ID_TYPE_FIELD": "text",
              "UF_VALUE_FIELD": "Текст 2",
              "UF_FILED_ANSWER": "фывфы@mail.ru",
              "UF_FIELD_FILLED": "true"
            },
            {
              "ID": "454",
              "UF_ID_QUESTION": "1524",
              "UF_ID_FIELD": "78ce0bf9-e1aa-4483-a45a-5c122cbddbb6",
              "UF_ID_TYPE_FIELD": "phone",
              "UF_VALUE_FIELD": "Телефон 2",
              "UF_FILED_ANSWER": "+7(123)123-12-31",
              "UF_FIELD_FILLED": "true"
            },
            {
              "ID": "455",
              "UF_ID_QUESTION": "1524",
              "UF_ID_FIELD": "2583bdba-96dd-4da2-ae2b-d4cc40ecd469",
              "UF_ID_TYPE_FIELD": "email",
              "UF_VALUE_FIELD": "Email 2",
              "UF_FILED_ANSWER": "фывфы@mail.ru",
              "UF_FIELD_FILLED": "true"
            },
            {
              "ID": "456",
              "UF_ID_QUESTION": "1524",
              "UF_ID_FIELD": "a088b845-d496-4aad-91b2-d9d461f409ed",
              "UF_ID_TYPE_FIELD": "textarea",
              "UF_VALUE_FIELD": "Область текста 2",
              "UF_FILED_ANSWER": "123123123",
              "UF_FIELD_FILLED": "true"
            }
          ]
        ],
        [
          [
            {
              "ID": "463",
              "UF_ID_QUESTION": "1536",
              "UF_ID_FIELD": "1",
              "UF_ID_TYPE_FIELD": "text",
              "UF_VALUE_FIELD": "Текст 2",
              "UF_FILED_ANSWER": "asdasd",
              "UF_FIELD_FILLED": "true"
            },
            {
              "ID": "464",
              "UF_ID_QUESTION": "1536",
              "UF_ID_FIELD": "78ce0bf9-e1aa-4483-a45a-5c122cbddbb6",
              "UF_ID_TYPE_FIELD": "phone",
              "UF_VALUE_FIELD": "Телефон 2",
              "UF_FILED_ANSWER": "+7(123)123-12-31",
              "UF_FIELD_FILLED": "true"
            },
            {
              "ID": "465",
              "UF_ID_QUESTION": "1536",
              "UF_ID_FIELD": "2583bdba-96dd-4da2-ae2b-d4cc40ecd469",
              "UF_ID_TYPE_FIELD": "email",
              "UF_VALUE_FIELD": "Email 2",
              "UF_FILED_ANSWER": "asdsa@mail.ru",
              "UF_FIELD_FILLED": "true"
            },
            {
              "ID": "466",
              "UF_ID_QUESTION": "1536",
              "UF_ID_FIELD": "a088b845-d496-4aad-91b2-d9d461f409ed",
              "UF_ID_TYPE_FIELD": "textarea",
              "UF_VALUE_FIELD": "Область текста 2",
              "UF_FILED_ANSWER": "123123",
              "UF_FIELD_FILLED": "true"
            }
          ]
        ],
        [
          [
            {
              "ID": "473",
              "UF_ID_QUESTION": "1548",
              "UF_ID_FIELD": "1",
              "UF_ID_TYPE_FIELD": "text",
              "UF_VALUE_FIELD": "Текст 2",
              "UF_FILED_ANSWER": "asdasd",
              "UF_FIELD_FILLED": "true"
            },
            {
              "ID": "474",
              "UF_ID_QUESTION": "1548",
              "UF_ID_FIELD": "78ce0bf9-e1aa-4483-a45a-5c122cbddbb6",
              "UF_ID_TYPE_FIELD": "phone",
              "UF_VALUE_FIELD": "Телефон 2",
              "UF_FILED_ANSWER": "+7(123)123-13-12",
              "UF_FIELD_FILLED": "true"
            },
            {
              "ID": "475",
              "UF_ID_QUESTION": "1548",
              "UF_ID_FIELD": "2583bdba-96dd-4da2-ae2b-d4cc40ecd469",
              "UF_ID_TYPE_FIELD": "email",
              "UF_VALUE_FIELD": "Email 2",
              "UF_FILED_ANSWER": "asdasd@mail.ru",
              "UF_FIELD_FILLED": "true"
            },
            {
              "ID": "476",
              "UF_ID_QUESTION": "1548",
              "UF_ID_FIELD": "a088b845-d496-4aad-91b2-d9d461f409ed",
              "UF_ID_TYPE_FIELD": "textarea",
              "UF_VALUE_FIELD": "Область текста 2",
              "UF_FILED_ANSWER": "123123",
              "UF_FIELD_FILLED": "true"
            }
          ]
        ],
        [
          [
            {
              "ID": "483",
              "UF_ID_QUESTION": "1560",
              "UF_ID_FIELD": "1",
              "UF_ID_TYPE_FIELD": "text",
              "UF_VALUE_FIELD": "Текст 2",
              "UF_FILED_ANSWER": "Поле имя 2",
              "UF_FIELD_FILLED": "true"
            },
            {
              "ID": "484",
              "UF_ID_QUESTION": "1560",
              "UF_ID_FIELD": "78ce0bf9-e1aa-4483-a45a-5c122cbddbb6",
              "UF_ID_TYPE_FIELD": "phone",
              "UF_VALUE_FIELD": "Телефон 2",
              "UF_FILED_ANSWER": "+7(222)222-22-22",
              "UF_FIELD_FILLED": "true"
            },
            {
              "ID": "485",
              "UF_ID_QUESTION": "1560",
              "UF_ID_FIELD": "2583bdba-96dd-4da2-ae2b-d4cc40ecd469",
              "UF_ID_TYPE_FIELD": "email",
              "UF_VALUE_FIELD": "Email 2",
              "UF_FILED_ANSWER": "email@mail.ru",
              "UF_FIELD_FILLED": "true"
            },
            {
              "ID": "486",
              "UF_ID_QUESTION": "1560",
              "UF_ID_FIELD": "a088b845-d496-4aad-91b2-d9d461f409ed",
              "UF_ID_TYPE_FIELD": "textarea",
              "UF_VALUE_FIELD": "Область текста 2",
              "UF_FILED_ANSWER": "Какой то текст 2",
              "UF_FIELD_FILLED": "true"
            }
          ]
        ],
        [
          [
            {
              "ID": "493",
              "UF_ID_QUESTION": "1572",
              "UF_ID_FIELD": "1",
              "UF_ID_TYPE_FIELD": "text",
              "UF_VALUE_FIELD": "Текст 2",
              "UF_FILED_ANSWER": "123123",
              "UF_FIELD_FILLED": "true"
            },
            {
              "ID": "494",
              "UF_ID_QUESTION": "1572",
              "UF_ID_FIELD": "78ce0bf9-e1aa-4483-a45a-5c122cbddbb6",
              "UF_ID_TYPE_FIELD": "phone",
              "UF_VALUE_FIELD": "Телефон 2",
              "UF_FILED_ANSWER": "+7(123)123-12-31",
              "UF_FIELD_FILLED": "true"
            },
            {
              "ID": "495",
              "UF_ID_QUESTION": "1572",
              "UF_ID_FIELD": "2583bdba-96dd-4da2-ae2b-d4cc40ecd469",
              "UF_ID_TYPE_FIELD": "email",
              "UF_VALUE_FIELD": "Email 2",
              "UF_FILED_ANSWER": "asdas@mail.ru",
              "UF_FIELD_FILLED": "true"
            },
            {
              "ID": "496",
              "UF_ID_QUESTION": "1572",
              "UF_ID_FIELD": "a088b845-d496-4aad-91b2-d9d461f409ed",
              "UF_ID_TYPE_FIELD": "textarea",
              "UF_VALUE_FIELD": "Область текста 2",
              "UF_FILED_ANSWER": "123123",
              "UF_FIELD_FILLED": "true"
            }
          ]
        ],
        [
          [
            {
              "ID": "503",
              "UF_ID_QUESTION": "1584",
              "UF_ID_FIELD": "1",
              "UF_ID_TYPE_FIELD": "text",
              "UF_VALUE_FIELD": "Текст 2",
              "UF_FILED_ANSWER": "asd@mail.ru",
              "UF_FIELD_FILLED": "true"
            },
            {
              "ID": "504",
              "UF_ID_QUESTION": "1584",
              "UF_ID_FIELD": "78ce0bf9-e1aa-4483-a45a-5c122cbddbb6",
              "UF_ID_TYPE_FIELD": "phone",
              "UF_VALUE_FIELD": "Телефон 2",
              "UF_FILED_ANSWER": "+7(123)123-31-23",
              "UF_FIELD_FILLED": "true"
            },
            {
              "ID": "505",
              "UF_ID_QUESTION": "1584",
              "UF_ID_FIELD": "2583bdba-96dd-4da2-ae2b-d4cc40ecd469",
              "UF_ID_TYPE_FIELD": "email",
              "UF_VALUE_FIELD": "Email 2",
              "UF_FILED_ANSWER": "asd@mail.ru",
              "UF_FIELD_FILLED": "true"
            },
            {
              "ID": "506",
              "UF_ID_QUESTION": "1584",
              "UF_ID_FIELD": "a088b845-d496-4aad-91b2-d9d461f409ed",
              "UF_ID_TYPE_FIELD": "textarea",
              "UF_VALUE_FIELD": "Область текста 2",
              "UF_FILED_ANSWER": "asd@mail.ru",
              "UF_FIELD_FILLED": "true"
            }
          ]
        ],
        [
          [
            {
              "ID": "513",
              "UF_ID_QUESTION": "1596",
              "UF_ID_FIELD": "1",
              "UF_ID_TYPE_FIELD": "text",
              "UF_VALUE_FIELD": "Текст 2",
              "UF_FILED_ANSWER": "Я текстовое поле которое есть",
              "UF_FIELD_FILLED": "true"
            },
            {
              "ID": "514",
              "UF_ID_QUESTION": "1596",
              "UF_ID_FIELD": "78ce0bf9-e1aa-4483-a45a-5c122cbddbb6",
              "UF_ID_TYPE_FIELD": "phone",
              "UF_VALUE_FIELD": "Телефон 2",
              "UF_FILED_ANSWER": "+7(222)222-22-22",
              "UF_FIELD_FILLED": "true"
            },
            {
              "ID": "515",
              "UF_ID_QUESTION": "1596",
              "UF_ID_FIELD": "2583bdba-96dd-4da2-ae2b-d4cc40ecd469",
              "UF_ID_TYPE_FIELD": "email",
              "UF_VALUE_FIELD": "Email 2",
              "UF_FILED_ANSWER": "MYSecondEmail@mail.ru",
              "UF_FIELD_FILLED": "true"
            },
            {
              "ID": "516",
              "UF_ID_QUESTION": "1596",
              "UF_ID_FIELD": "a088b845-d496-4aad-91b2-d9d461f409ed",
              "UF_ID_TYPE_FIELD": "textarea",
              "UF_VALUE_FIELD": "Область текста 2",
              "UF_FILED_ANSWER": "Какой то рандомный текст в другом поле",
              "UF_FIELD_FILLED": "true"
            }
          ]
        ]
      ],
      "65989748-d47a-45b9-b32c-b4ae4aaee04e": [
        [
          [
            {
              "ID": "457",
              "UF_ID_QUESTION": "1525",
              "UF_ID_FIELD": "1",
              "UF_ID_TYPE_FIELD": "text",
              "UF_VALUE_FIELD": "текст",
              "UF_FILED_ANSWER": "фывфы@mail.ru",
              "UF_FIELD_FILLED": "true"
            },
            {
              "ID": "458",
              "UF_ID_QUESTION": "1525",
              "UF_ID_FIELD": "a55a6b48-1a53-44ba-a44d-835f501c6a7b",
              "UF_ID_TYPE_FIELD": "phone",
              "UF_VALUE_FIELD": "Телефон",
              "UF_FILED_ANSWER": "+7(123)123-12-31",
              "UF_FIELD_FILLED": "true"
            }
          ]
        ],
        [
          [
            {
              "ID": "467",
              "UF_ID_QUESTION": "1537",
              "UF_ID_FIELD": "1",
              "UF_ID_TYPE_FIELD": "text",
              "UF_VALUE_FIELD": "текст",
              "UF_FILED_ANSWER": "fhjkfghjk",
              "UF_FIELD_FILLED": "true"
            },
            {
              "ID": "468",
              "UF_ID_QUESTION": "1537",
              "UF_ID_FIELD": "a55a6b48-1a53-44ba-a44d-835f501c6a7b",
              "UF_ID_TYPE_FIELD": "phone",
              "UF_VALUE_FIELD": "Телефон",
              "UF_FILED_ANSWER": "+7(342)342-34-23",
              "UF_FIELD_FILLED": "true"
            }
          ]
        ],
        [
          [
            {
              "ID": "477",
              "UF_ID_QUESTION": "1549",
              "UF_ID_FIELD": "1",
              "UF_ID_TYPE_FIELD": "text",
              "UF_VALUE_FIELD": "текст",
              "UF_FILED_ANSWER": "asdasd",
              "UF_FIELD_FILLED": "true"
            },
            {
              "ID": "478",
              "UF_ID_QUESTION": "1549",
              "UF_ID_FIELD": "a55a6b48-1a53-44ba-a44d-835f501c6a7b",
              "UF_ID_TYPE_FIELD": "phone",
              "UF_VALUE_FIELD": "Телефон",
              "UF_FILED_ANSWER": "+7(123)123-12-31",
              "UF_FIELD_FILLED": "true"
            }
          ]
        ],
        [
          [
            {
              "ID": "487",
              "UF_ID_QUESTION": "1561",
              "UF_ID_FIELD": "1",
              "UF_ID_TYPE_FIELD": "text",
              "UF_VALUE_FIELD": "текст",
              "UF_FILED_ANSWER": "Имя 3",
              "UF_FIELD_FILLED": "true"
            },
            {
              "ID": "488",
              "UF_ID_QUESTION": "1561",
              "UF_ID_FIELD": "a55a6b48-1a53-44ba-a44d-835f501c6a7b",
              "UF_ID_TYPE_FIELD": "phone",
              "UF_VALUE_FIELD": "Телефон",
              "UF_FILED_ANSWER": "+7(333)333-33-33",
              "UF_FIELD_FILLED": "true"
            }
          ]
        ],
        [
          [
            {
              "ID": "497",
              "UF_ID_QUESTION": "1573",
              "UF_ID_FIELD": "1",
              "UF_ID_TYPE_FIELD": "text",
              "UF_VALUE_FIELD": "текст",
              "UF_FILED_ANSWER": "123123",
              "UF_FIELD_FILLED": "true"
            },
            {
              "ID": "498",
              "UF_ID_QUESTION": "1573",
              "UF_ID_FIELD": "a55a6b48-1a53-44ba-a44d-835f501c6a7b",
              "UF_ID_TYPE_FIELD": "phone",
              "UF_VALUE_FIELD": "Телефон",
              "UF_FILED_ANSWER": "+7(123)123-12-31",
              "UF_FIELD_FILLED": "true"
            }
          ]
        ],
        [
          [
            {
              "ID": "507",
              "UF_ID_QUESTION": "1585",
              "UF_ID_FIELD": "1",
              "UF_ID_TYPE_FIELD": "text",
              "UF_VALUE_FIELD": "текст",
              "UF_FILED_ANSWER": "asd@mail.ru",
              "UF_FIELD_FILLED": "true"
            },
            {
              "ID": "508",
              "UF_ID_QUESTION": "1585",
              "UF_ID_FIELD": "a55a6b48-1a53-44ba-a44d-835f501c6a7b",
              "UF_ID_TYPE_FIELD": "phone",
              "UF_VALUE_FIELD": "Телефон",
              "UF_FILED_ANSWER": "+7(123)123-12-31",
              "UF_FIELD_FILLED": "true"
            }
          ]
        ],
        [
          [
            {
              "ID": "517",
              "UF_ID_QUESTION": "1597",
              "UF_ID_FIELD": "1",
              "UF_ID_TYPE_FIELD": "text",
              "UF_VALUE_FIELD": "текст",
              "UF_FILED_ANSWER": "123123",
              "UF_FIELD_FILLED": "true"
            },
            {
              "ID": "518",
              "UF_ID_QUESTION": "1597",
              "UF_ID_FIELD": "a55a6b48-1a53-44ba-a44d-835f501c6a7b",
              "UF_ID_TYPE_FIELD": "phone",
              "UF_VALUE_FIELD": "Телефон",
              "UF_FILED_ANSWER": "+7(123)123-12-31",
              "UF_FIELD_FILLED": "true"
            }
          ]
        ]
      ]
    },
    "QUESTION": [
      [
        {
          "ID": "1515",
          "UF_ID_RESULT": "479",
          "UF_ID_QUESTION": "a9234e5a-fe09-4a68-be31-55247ad9749c",
          "UF_QUESTION_TYPE": "single-choice",
          "UF_VARIANT_TYPE": "",
          "UF_ID_PAGE": "264",
          "PARAMS": {
            "NAME": [
              {
                "insert": "Одиночный выбор\n"
              }
            ],
            "TYPENAME": "Одиночный выбор",
            "GENERAL_RANGE_START": null,
            "GENERAL_RANGE_END": null
          },
          "VARIANTS": [
            {
              "ID": "5414",
              "UF_ID_QUESTION": "1515",
              "UF_ID_VARIANT": "1",
              "UF_VARIANT_VALUE": "Одиночный выбор 1"
            },
            {
              "ID": "5415",
              "UF_ID_QUESTION": "1515",
              "UF_ID_VARIANT": "2",
              "UF_VARIANT_VALUE": "Одиночный выбор 2"
            },
            {
              "ID": "5416",
              "UF_ID_QUESTION": "1515",
              "UF_ID_VARIANT": "08ce1c9d-5867-4038-857a-300732d78d9c",
              "UF_VARIANT_VALUE": "Одиночный выбор 3"
            }
          ],
          "ANSWERS": {
            "CORRECT_ANSWER": [""],
            "USER_ANSWER": {
              "1": {
                "TEXT": "Одиночный выбор 1",
                "COUNT_ANSWER": 2,
                "PROCENT": 28.6
              },
              "2": {
                "TEXT": "Одиночный выбор 2",
                "COUNT_ANSWER": 3,
                "PROCENT": 42.9
              },
              "08ce1c9d-5867-4038-857a-300732d78d9c": {
                "TEXT": "Одиночный выбор 3",
                "COUNT_ANSWER": 2,
                "PROCENT": 28.6
              }
            }
          }
        },
        {
          "ID": "1516",
          "UF_ID_RESULT": "479",
          "UF_ID_QUESTION": "f042fd90-5c16-4ccf-be11-6855dc62bcd5",
          "UF_QUESTION_TYPE": "drop-down-list",
          "UF_VARIANT_TYPE": "",
          "UF_ID_PAGE": "264",
          "PARAMS": {
            "NAME": [
              {
                "insert": "Выпадающий список\n"
              }
            ],
            "TYPENAME": "Выпадающий список",
            "GENERAL_RANGE_START": null,
            "GENERAL_RANGE_END": null
          },
          "VARIANTS": [
            {
              "ID": "5417",
              "UF_ID_QUESTION": "1516",
              "UF_ID_VARIANT": "1",
              "UF_VARIANT_VALUE": "Выпадающий список 1"
            },
            {
              "ID": "5418",
              "UF_ID_QUESTION": "1516",
              "UF_ID_VARIANT": "2",
              "UF_VARIANT_VALUE": "Выпадающий список 2"
            },
            {
              "ID": "5419",
              "UF_ID_QUESTION": "1516",
              "UF_ID_VARIANT": "4a21b98b-dd7c-4124-b106-24b612fcb673",
              "UF_VARIANT_VALUE": "Выпадающий список 3"
            }
          ],
          "ANSWERS": {
            "CORRECT_ANSWER": [""],
            "USER_ANSWER": {
              "1": {
                "TEXT": "Выпадающий список 1",
                "COUNT_ANSWER": 2,
                "PROCENT": 28.6
              },
              "2": {
                "TEXT": "Выпадающий список 2",
                "COUNT_ANSWER": 3,
                "PROCENT": 42.9
              },
              "4a21b98b-dd7c-4124-b106-24b612fcb673": {
                "TEXT": "Выпадающий список 3",
                "COUNT_ANSWER": 2,
                "PROCENT": 28.6
              }
            }
          }
        },
        {
          "ID": "1517",
          "UF_ID_RESULT": "479",
          "UF_ID_QUESTION": "c72e884d-dc71-4af4-81f7-abc32d392000",
          "UF_QUESTION_TYPE": "multiple-drop-down-list",
          "UF_VARIANT_TYPE": "",
          "UF_ID_PAGE": "264",
          "PARAMS": {
            "NAME": [
              {
                "insert": "Множественный вып. список\n"
              }
            ],
            "TYPENAME": "Множественный вып. список",
            "GENERAL_RANGE_START": null,
            "GENERAL_RANGE_END": null
          },
          "VARIANTS": [
            {
              "ID": "5420",
              "UF_ID_QUESTION": "1517",
              "UF_ID_VARIANT": "1",
              "UF_VARIANT_VALUE": "Множественный вып. список 1"
            },
            {
              "ID": "5421",
              "UF_ID_QUESTION": "1517",
              "UF_ID_VARIANT": "2",
              "UF_VARIANT_VALUE": "Множественный вып. список 2"
            },
            {
              "ID": "5422",
              "UF_ID_QUESTION": "1517",
              "UF_ID_VARIANT": "0b69d1f3-37d2-4455-924b-958d27865c85",
              "UF_VARIANT_VALUE": "Множественный вып. список 3"
            }
          ],
          "ANSWERS": {
            "CORRECT_ANSWER": [""],
            "USER_ANSWER": {
              "1": {
                "TEXT": "Множественный вып. список 1",
                "COUNT_ANSWER": 4,
                "PROCENT": 44.4
              },
              "2": {
                "TEXT": "Множественный вып. список 2",
                "COUNT_ANSWER": 3,
                "PROCENT": 33.3
              },
              "0b69d1f3-37d2-4455-924b-958d27865c85": {
                "TEXT": "Множественный вып. список 3",
                "COUNT_ANSWER": 2,
                "PROCENT": 22.2
              }
            }
          }
        },
        {
          "ID": "1518",
          "UF_ID_RESULT": "479",
          "UF_ID_QUESTION": "09e72ec1-d7be-4f4e-80e3-3b34b5831702",
          "UF_QUESTION_TYPE": "multiple-choice",
          "UF_VARIANT_TYPE": "",
          "UF_ID_PAGE": "264",
          "PARAMS": {
            "NAME": [
              {
                "insert": "Множественный выбор\n"
              }
            ],
            "TYPENAME": "Множественный выбор",
            "GENERAL_RANGE_START": null,
            "GENERAL_RANGE_END": null
          },
          "VARIANTS": [
            {
              "ID": "5423",
              "UF_ID_QUESTION": "1518",
              "UF_ID_VARIANT": "1",
              "UF_VARIANT_VALUE": "Множественный выбор 1"
            },
            {
              "ID": "5424",
              "UF_ID_QUESTION": "1518",
              "UF_ID_VARIANT": "2",
              "UF_VARIANT_VALUE": "Множественный выбор 2"
            },
            {
              "ID": "5425",
              "UF_ID_QUESTION": "1518",
              "UF_ID_VARIANT": "d5e56cd8-5657-426b-8297-3d2c20a4cc29",
              "UF_VARIANT_VALUE": "Множественный выбор 3"
            },
            {
              "ID": "5426",
              "UF_ID_QUESTION": "1518",
              "UF_ID_VARIANT": "69ad2172-dec9-473b-8e4c-3669016a1146",
              "UF_VARIANT_VALUE": "Множественный выбор 4"
            }
          ],
          "ANSWERS": {
            "CORRECT_ANSWER": [""],
            "USER_ANSWER": {
              "1": {
                "TEXT": "Множественный выбор 1",
                "COUNT_ANSWER": 4,
                "PROCENT": 33.3
              },
              "2": {
                "TEXT": "Множественный выбор 2",
                "COUNT_ANSWER": 3,
                "PROCENT": 25
              },
              "d5e56cd8-5657-426b-8297-3d2c20a4cc29": {
                "TEXT": "Множественный выбор 3",
                "COUNT_ANSWER": 3,
                "PROCENT": 25
              },
              "69ad2172-dec9-473b-8e4c-3669016a1146": {
                "TEXT": "Множественный выбор 4",
                "COUNT_ANSWER": 2,
                "PROCENT": 16.7
              }
            }
          }
        },
        {
          "ID": "1519",
          "UF_ID_RESULT": "479",
          "UF_ID_QUESTION": "62c8a9e6-fc36-4cd9-b5e1-e8240d4cb568",
          "UF_QUESTION_TYPE": "ranging",
          "UF_VARIANT_TYPE": "",
          "UF_ID_PAGE": "264",
          "PARAMS": {
            "NAME": [
              {
                "insert": "Ранжирование\n"
              }
            ],
            "TYPENAME": "Ранжирование",
            "GENERAL_RANGE_START": null,
            "GENERAL_RANGE_END": null
          },
          "VARIANTS": [
            {
              "ID": "5427",
              "UF_ID_QUESTION": "1519",
              "UF_ID_VARIANT": "1",
              "UF_VARIANT_VALUE": "Ранжирование 1"
            },
            {
              "ID": "5428",
              "UF_ID_QUESTION": "1519",
              "UF_ID_VARIANT": "2",
              "UF_VARIANT_VALUE": "Ранжирование 2"
            },
            {
              "ID": "5429",
              "UF_ID_QUESTION": "1519",
              "UF_ID_VARIANT": "9090ad2e-c9dd-476f-b5ad-4d0ddbc6f454",
              "UF_VARIANT_VALUE": "Ранжирование 3"
            },
            {
              "ID": "5430",
              "UF_ID_QUESTION": "1519",
              "UF_ID_VARIANT": "7538fd5e-6b2b-40ed-91d2-e65c3aed5c6f",
              "UF_VARIANT_VALUE": "Ранжирование 4"
            },
            {
              "ID": "5431",
              "UF_ID_QUESTION": "1519",
              "UF_ID_VARIANT": "b81592ef-86ba-4ee9-a48c-f9ae73d12d61",
              "UF_VARIANT_VALUE": "Ранжирование 5"
            },
            {
              "ID": "5432",
              "UF_ID_QUESTION": "1519",
              "UF_ID_VARIANT": "f6f3953e-b4ca-443e-9b4b-d7a2d2a0746f",
              "UF_VARIANT_VALUE": "Ранжирование 6"
            },
            {
              "ID": "5433",
              "UF_ID_QUESTION": "1519",
              "UF_ID_VARIANT": "a1bc2f76-5043-4574-a81b-e40b6e577307",
              "UF_VARIANT_VALUE": "Ранжирование 7"
            },
            {
              "ID": "5434",
              "UF_ID_QUESTION": "1519",
              "UF_ID_VARIANT": "d4990609-06a0-4cdb-b6b7-b1981fa29d6b",
              "UF_VARIANT_VALUE": "Ранжирование 8"
            },
            {
              "ID": "5435",
              "UF_ID_QUESTION": "1519",
              "UF_ID_VARIANT": "1cd9d838-8360-4ff6-af2c-3ad6b6261516",
              "UF_VARIANT_VALUE": "Ранжирование 9"
            }
          ],
          "ANSWERS": {
            "USER_ANSWER": {
              "1": {
                "TEXT": "Ранжирование 1",
                "COUNT_ANSWER": 1,
                "PROC": 2,
                "INCORRECT": {
                  "2": {
                    "TEXT": "Ранжирование 2",
                    "COUNT_ANSWER": 6,
                    "PROC": 11.8
                  },
                  "a1bc2f76-5043-4574-a81b-e40b6e577307": {
                    "TEXT": "Ранжирование 7",
                    "COUNT_ANSWER": 7,
                    "PROC": 13.7
                  },
                  "b81592ef-86ba-4ee9-a48c-f9ae73d12d61": {
                    "TEXT": "Ранжирование 5",
                    "COUNT_ANSWER": 6,
                    "PROC": 11.8
                  },
                  "9090ad2e-c9dd-476f-b5ad-4d0ddbc6f454": {
                    "TEXT": "Ранжирование 3",
                    "COUNT_ANSWER": 5,
                    "PROC": 9.8
                  },
                  "7538fd5e-6b2b-40ed-91d2-e65c3aed5c6f": {
                    "TEXT": "Ранжирование 4",
                    "COUNT_ANSWER": 6,
                    "PROC": 11.8
                  },
                  "1cd9d838-8360-4ff6-af2c-3ad6b6261516": {
                    "TEXT": "Ранжирование 9",
                    "COUNT_ANSWER": 6,
                    "PROC": 11.8
                  },
                  "f6f3953e-b4ca-443e-9b4b-d7a2d2a0746f": {
                    "TEXT": "Ранжирование 6",
                    "COUNT_ANSWER": 7,
                    "PROC": 13.7
                  },
                  "d4990609-06a0-4cdb-b6b7-b1981fa29d6b": {
                    "TEXT": "Ранжирование 8",
                    "COUNT_ANSWER": 7,
                    "PROC": 13.7
                  }
                }
              },
              "2": {
                "TEXT": "Ранжирование 2",
                "COUNT_ANSWER": 1,
                "PROC": 2,
                "INCORRECT": {
                  "1": {
                    "TEXT": "Ранжирование 1",
                    "COUNT_ANSWER": 6,
                    "PROC": 11.8
                  },
                  "b81592ef-86ba-4ee9-a48c-f9ae73d12d61": {
                    "TEXT": "Ранжирование 5",
                    "COUNT_ANSWER": 7,
                    "PROC": 13.7
                  },
                  "9090ad2e-c9dd-476f-b5ad-4d0ddbc6f454": {
                    "TEXT": "Ранжирование 3",
                    "COUNT_ANSWER": 6,
                    "PROC": 11.8
                  },
                  "7538fd5e-6b2b-40ed-91d2-e65c3aed5c6f": {
                    "TEXT": "Ранжирование 4",
                    "COUNT_ANSWER": 5,
                    "PROC": 9.8
                  },
                  "1cd9d838-8360-4ff6-af2c-3ad6b6261516": {
                    "TEXT": "Ранжирование 9",
                    "COUNT_ANSWER": 7,
                    "PROC": 13.7
                  },
                  "f6f3953e-b4ca-443e-9b4b-d7a2d2a0746f": {
                    "TEXT": "Ранжирование 6",
                    "COUNT_ANSWER": 7,
                    "PROC": 13.7
                  },
                  "d4990609-06a0-4cdb-b6b7-b1981fa29d6b": {
                    "TEXT": "Ранжирование 8",
                    "COUNT_ANSWER": 6,
                    "PROC": 11.8
                  },
                  "a1bc2f76-5043-4574-a81b-e40b6e577307": {
                    "TEXT": "Ранжирование 7",
                    "COUNT_ANSWER": 6,
                    "PROC": 11.8
                  }
                }
              },
              "9090ad2e-c9dd-476f-b5ad-4d0ddbc6f454": {
                "TEXT": "Ранжирование 3",
                "COUNT_ANSWER": 1,
                "PROC": 2,
                "INCORRECT": {
                  "1": {
                    "TEXT": "Ранжирование 1",
                    "COUNT_ANSWER": 6,
                    "PROC": 11.8
                  },
                  "2": {
                    "TEXT": "Ранжирование 2",
                    "COUNT_ANSWER": 6,
                    "PROC": 11.8
                  },
                  "a1bc2f76-5043-4574-a81b-e40b6e577307": {
                    "TEXT": "Ранжирование 7",
                    "COUNT_ANSWER": 7,
                    "PROC": 13.7
                  },
                  "b81592ef-86ba-4ee9-a48c-f9ae73d12d61": {
                    "TEXT": "Ранжирование 5",
                    "COUNT_ANSWER": 7,
                    "PROC": 13.7
                  },
                  "7538fd5e-6b2b-40ed-91d2-e65c3aed5c6f": {
                    "TEXT": "Ранжирование 4",
                    "COUNT_ANSWER": 7,
                    "PROC": 13.7
                  },
                  "1cd9d838-8360-4ff6-af2c-3ad6b6261516": {
                    "TEXT": "Ранжирование 9",
                    "COUNT_ANSWER": 6,
                    "PROC": 11.8
                  },
                  "f6f3953e-b4ca-443e-9b4b-d7a2d2a0746f": {
                    "TEXT": "Ранжирование 6",
                    "COUNT_ANSWER": 6,
                    "PROC": 11.8
                  },
                  "d4990609-06a0-4cdb-b6b7-b1981fa29d6b": {
                    "TEXT": "Ранжирование 8",
                    "COUNT_ANSWER": 5,
                    "PROC": 9.8
                  }
                }
              },
              "7538fd5e-6b2b-40ed-91d2-e65c3aed5c6f": {
                "TEXT": "Ранжирование 4",
                "COUNT_ANSWER": 2,
                "PROC": 3.8,
                "INCORRECT": {
                  "1": {
                    "TEXT": "Ранжирование 1",
                    "COUNT_ANSWER": 6,
                    "PROC": 11.3
                  },
                  "2": {
                    "TEXT": "Ранжирование 2",
                    "COUNT_ANSWER": 6,
                    "PROC": 11.3
                  },
                  "a1bc2f76-5043-4574-a81b-e40b6e577307": {
                    "TEXT": "Ранжирование 7",
                    "COUNT_ANSWER": 7,
                    "PROC": 13.2
                  },
                  "9090ad2e-c9dd-476f-b5ad-4d0ddbc6f454": {
                    "TEXT": "Ранжирование 3",
                    "COUNT_ANSWER": 6,
                    "PROC": 11.3
                  },
                  "1cd9d838-8360-4ff6-af2c-3ad6b6261516": {
                    "TEXT": "Ранжирование 9",
                    "COUNT_ANSWER": 7,
                    "PROC": 13.2
                  },
                  "f6f3953e-b4ca-443e-9b4b-d7a2d2a0746f": {
                    "TEXT": "Ранжирование 6",
                    "COUNT_ANSWER": 6,
                    "PROC": 11.3
                  },
                  "d4990609-06a0-4cdb-b6b7-b1981fa29d6b": {
                    "TEXT": "Ранжирование 8",
                    "COUNT_ANSWER": 7,
                    "PROC": 13.2
                  },
                  "b81592ef-86ba-4ee9-a48c-f9ae73d12d61": {
                    "TEXT": "Ранжирование 5",
                    "COUNT_ANSWER": 6,
                    "PROC": 11.3
                  }
                }
              },
              "b81592ef-86ba-4ee9-a48c-f9ae73d12d61": {
                "TEXT": "Ранжирование 5",
                "COUNT_ANSWER": 1,
                "PROC": 2,
                "INCORRECT": {
                  "1": {
                    "TEXT": "Ранжирование 1",
                    "COUNT_ANSWER": 6,
                    "PROC": 11.8
                  },
                  "2": {
                    "TEXT": "Ранжирование 2",
                    "COUNT_ANSWER": 6,
                    "PROC": 11.8
                  },
                  "a1bc2f76-5043-4574-a81b-e40b6e577307": {
                    "TEXT": "Ранжирование 7",
                    "COUNT_ANSWER": 6,
                    "PROC": 11.8
                  },
                  "7538fd5e-6b2b-40ed-91d2-e65c3aed5c6f": {
                    "TEXT": "Ранжирование 4",
                    "COUNT_ANSWER": 6,
                    "PROC": 11.8
                  },
                  "1cd9d838-8360-4ff6-af2c-3ad6b6261516": {
                    "TEXT": "Ранжирование 9",
                    "COUNT_ANSWER": 7,
                    "PROC": 13.7
                  },
                  "f6f3953e-b4ca-443e-9b4b-d7a2d2a0746f": {
                    "TEXT": "Ранжирование 6",
                    "COUNT_ANSWER": 6,
                    "PROC": 11.8
                  },
                  "d4990609-06a0-4cdb-b6b7-b1981fa29d6b": {
                    "TEXT": "Ранжирование 8",
                    "COUNT_ANSWER": 7,
                    "PROC": 13.7
                  },
                  "9090ad2e-c9dd-476f-b5ad-4d0ddbc6f454": {
                    "TEXT": "Ранжирование 3",
                    "COUNT_ANSWER": 6,
                    "PROC": 11.8
                  }
                }
              },
              "f6f3953e-b4ca-443e-9b4b-d7a2d2a0746f": {
                "TEXT": "Ранжирование 6",
                "COUNT_ANSWER": 1,
                "PROC": 2,
                "INCORRECT": {
                  "1": {
                    "TEXT": "Ранжирование 1",
                    "COUNT_ANSWER": 7,
                    "PROC": 13.7
                  },
                  "2": {
                    "TEXT": "Ранжирование 2",
                    "COUNT_ANSWER": 7,
                    "PROC": 13.7
                  },
                  "a1bc2f76-5043-4574-a81b-e40b6e577307": {
                    "TEXT": "Ранжирование 7",
                    "COUNT_ANSWER": 7,
                    "PROC": 13.7
                  },
                  "b81592ef-86ba-4ee9-a48c-f9ae73d12d61": {
                    "TEXT": "Ранжирование 5",
                    "COUNT_ANSWER": 4,
                    "PROC": 7.8
                  },
                  "9090ad2e-c9dd-476f-b5ad-4d0ddbc6f454": {
                    "TEXT": "Ранжирование 3",
                    "COUNT_ANSWER": 6,
                    "PROC": 11.8
                  },
                  "1cd9d838-8360-4ff6-af2c-3ad6b6261516": {
                    "TEXT": "Ранжирование 9",
                    "COUNT_ANSWER": 6,
                    "PROC": 11.8
                  },
                  "d4990609-06a0-4cdb-b6b7-b1981fa29d6b": {
                    "TEXT": "Ранжирование 8",
                    "COUNT_ANSWER": 7,
                    "PROC": 13.7
                  },
                  "7538fd5e-6b2b-40ed-91d2-e65c3aed5c6f": {
                    "TEXT": "Ранжирование 4",
                    "COUNT_ANSWER": 6,
                    "PROC": 11.8
                  }
                }
              },
              "a1bc2f76-5043-4574-a81b-e40b6e577307": {
                "TEXT": "Ранжирование 7",
                "COUNT_ANSWER": 4,
                "PROC": 7,
                "INCORRECT": {
                  "1": {
                    "TEXT": "Ранжирование 1",
                    "COUNT_ANSWER": 7,
                    "PROC": 12.3
                  },
                  "2": {
                    "TEXT": "Ранжирование 2",
                    "COUNT_ANSWER": 6,
                    "PROC": 10.5
                  },
                  "b81592ef-86ba-4ee9-a48c-f9ae73d12d61": {
                    "TEXT": "Ранжирование 5",
                    "COUNT_ANSWER": 7,
                    "PROC": 12.3
                  },
                  "9090ad2e-c9dd-476f-b5ad-4d0ddbc6f454": {
                    "TEXT": "Ранжирование 3",
                    "COUNT_ANSWER": 7,
                    "PROC": 12.3
                  },
                  "7538fd5e-6b2b-40ed-91d2-e65c3aed5c6f": {
                    "TEXT": "Ранжирование 4",
                    "COUNT_ANSWER": 7,
                    "PROC": 12.3
                  },
                  "f6f3953e-b4ca-443e-9b4b-d7a2d2a0746f": {
                    "TEXT": "Ранжирование 6",
                    "COUNT_ANSWER": 6,
                    "PROC": 10.5
                  },
                  "d4990609-06a0-4cdb-b6b7-b1981fa29d6b": {
                    "TEXT": "Ранжирование 8",
                    "COUNT_ANSWER": 7,
                    "PROC": 12.3
                  },
                  "1cd9d838-8360-4ff6-af2c-3ad6b6261516": {
                    "TEXT": "Ранжирование 9",
                    "COUNT_ANSWER": 6,
                    "PROC": 10.5
                  }
                }
              },
              "d4990609-06a0-4cdb-b6b7-b1981fa29d6b": {
                "TEXT": "Ранжирование 8",
                "COUNT_ANSWER": 3,
                "PROC": 5.5,
                "INCORRECT": {
                  "1": {
                    "TEXT": "Ранжирование 1",
                    "COUNT_ANSWER": 5,
                    "PROC": 9.1
                  },
                  "2": {
                    "TEXT": "Ранжирование 2",
                    "COUNT_ANSWER": 7,
                    "PROC": 12.7
                  },
                  "a1bc2f76-5043-4574-a81b-e40b6e577307": {
                    "TEXT": "Ранжирование 7",
                    "COUNT_ANSWER": 6,
                    "PROC": 10.9
                  },
                  "b81592ef-86ba-4ee9-a48c-f9ae73d12d61": {
                    "TEXT": "Ранжирование 5",
                    "COUNT_ANSWER": 7,
                    "PROC": 12.7
                  },
                  "9090ad2e-c9dd-476f-b5ad-4d0ddbc6f454": {
                    "TEXT": "Ранжирование 3",
                    "COUNT_ANSWER": 7,
                    "PROC": 12.7
                  },
                  "7538fd5e-6b2b-40ed-91d2-e65c3aed5c6f": {
                    "TEXT": "Ранжирование 4",
                    "COUNT_ANSWER": 7,
                    "PROC": 12.7
                  },
                  "1cd9d838-8360-4ff6-af2c-3ad6b6261516": {
                    "TEXT": "Ранжирование 9",
                    "COUNT_ANSWER": 7,
                    "PROC": 12.7
                  },
                  "f6f3953e-b4ca-443e-9b4b-d7a2d2a0746f": {
                    "TEXT": "Ранжирование 6",
                    "COUNT_ANSWER": 6,
                    "PROC": 10.9
                  }
                }
              },
              "1cd9d838-8360-4ff6-af2c-3ad6b6261516": {
                "TEXT": "Ранжирование 9",
                "COUNT_ANSWER": 3,
                "PROC": 5.5,
                "INCORRECT": {
                  "1": {
                    "TEXT": "Ранжирование 1",
                    "COUNT_ANSWER": 7,
                    "PROC": 12.7
                  },
                  "2": {
                    "TEXT": "Ранжирование 2",
                    "COUNT_ANSWER": 6,
                    "PROC": 10.9
                  },
                  "a1bc2f76-5043-4574-a81b-e40b6e577307": {
                    "TEXT": "Ранжирование 7",
                    "COUNT_ANSWER": 7,
                    "PROC": 12.7
                  },
                  "b81592ef-86ba-4ee9-a48c-f9ae73d12d61": {
                    "TEXT": "Ранжирование 5",
                    "COUNT_ANSWER": 6,
                    "PROC": 10.9
                  },
                  "9090ad2e-c9dd-476f-b5ad-4d0ddbc6f454": {
                    "TEXT": "Ранжирование 3",
                    "COUNT_ANSWER": 7,
                    "PROC": 12.7
                  },
                  "7538fd5e-6b2b-40ed-91d2-e65c3aed5c6f": {
                    "TEXT": "Ранжирование 4",
                    "COUNT_ANSWER": 7,
                    "PROC": 12.7
                  },
                  "f6f3953e-b4ca-443e-9b4b-d7a2d2a0746f": {
                    "TEXT": "Ранжирование 6",
                    "COUNT_ANSWER": 6,
                    "PROC": 10.9
                  },
                  "d4990609-06a0-4cdb-b6b7-b1981fa29d6b": {
                    "TEXT": "Ранжирование 8",
                    "COUNT_ANSWER": 6,
                    "PROC": 10.9
                  }
                }
              }
            }
          }
        },
        {
          "ID": "1520",
          "UF_ID_RESULT": "479",
          "UF_ID_QUESTION": "0f972123-85ad-4bbb-bd23-2b2ec2b5f1d1",
          "UF_QUESTION_TYPE": "range-selection",
          "UF_VARIANT_TYPE": "",
          "UF_ID_PAGE": "264",
          "PARAMS": {
            "NAME": [
              {
                "insert": "Выбор диапазона\n"
              }
            ],
            "TYPENAME": "Выбор диапазона",
            "GENERAL_RANGE_START": 100,
            "GENERAL_RANGE_END": 1000
          },
          "VARIANTS": null,
          "ANSWERS": {
            "START": ["262", "350", "329", "363", "274", "290", "289"],
            "END": ["1000", "802", "745", "799", "753", "680", "857"],
            "GEN_START_RANGE": 308,
            "GEN_END_RANGE": 805,
            "GEN_COUNT_ANSW": 7,
            "RANGE5": false,
            "RANGE10": false
          }
        },
        {
          "ID": "1521",
          "UF_ID_RESULT": "479",
          "UF_ID_QUESTION": "84feebae-f4e2-42b9-b80c-5b9e6f50ce36",
          "UF_QUESTION_TYPE": "date",
          "UF_VARIANT_TYPE": "",
          "UF_ID_PAGE": "264",
          "PARAMS": {
            "NAME": [
              {
                "insert": "Дата\n"
              }
            ],
            "TYPENAME": "Дата",
            "GENERAL_RANGE_START": null,
            "GENERAL_RANGE_END": null
          },
          "VARIANTS": null,
          "ANSWERS": {
            "CORRECT_ANSWER": [""],
            "USER_ANSWER": [
              {
                "TEXT": "2024-01-17T08:57:00.000Z",
                "COUNT_ANSWER": 1,
                "PROCENT": 14.3
              },
              {
                "TEXT": "2024-01-09T05:36:00.000Z",
                "COUNT_ANSWER": 1,
                "PROCENT": 14.3
              },
              {
                "TEXT": "2024-01-03T05:38:00.000Z",
                "COUNT_ANSWER": 1,
                "PROCENT": 14.3
              },
              {
                "TEXT": "2024-01-19T05:58:00.000Z",
                "COUNT_ANSWER": 1,
                "PROCENT": 14.3
              },
              {
                "TEXT": "2024-01-17T08:36:00.000Z",
                "COUNT_ANSWER": 1,
                "PROCENT": 14.3
              },
              {
                "TEXT": "2024-01-10T10:50:00.000Z",
                "COUNT_ANSWER": 1,
                "PROCENT": 14.3
              },
              {
                "TEXT": "2024-01-01T10:22:00.000Z",
                "COUNT_ANSWER": 1,
                "PROCENT": 14.3
              }
            ]
          }
        },
        {
          "ID": "1522",
          "UF_ID_RESULT": "479",
          "UF_ID_QUESTION": "37eae9a9-bf38-4d9a-8bab-63e27bb36614",
          "UF_QUESTION_TYPE": "date",
          "UF_VARIANT_TYPE": "",
          "UF_ID_PAGE": "264",
          "PARAMS": {
            "NAME": [
              {
                "insert": "Дата диапазон дат\n"
              }
            ],
            "TYPENAME": "Дата",
            "GENERAL_RANGE_START": null,
            "GENERAL_RANGE_END": null
          },
          "VARIANTS": null,
          "ANSWERS": {
            "CORRECT_ANSWER": [""],
            "USER_ANSWER": [
              {
                "TEXT": "Wed Jan 03 2024 14:57:00 GMT+0600 (Восточный Казахстан)-Wed Jan 17 2024 14:57:00 GMT+0600 (Восточный Казахстан)",
                "COUNT_ANSWER": 1,
                "PROCENT": 14.3
              },
              {
                "TEXT": "Wed Jan 03 2024 11:36:00 GMT+0600 (Восточный Казахстан)-Wed Jan 24 2024 11:36:00 GMT+0600 (Восточный Казахстан)",
                "COUNT_ANSWER": 1,
                "PROCENT": 14.3
              },
              {
                "TEXT": "Wed Jan 03 2024 11:38:00 GMT+0600 (Восточный Казахстан)-Wed Jan 17 2024 11:38:00 GMT+0600 (Восточный Казахстан)",
                "COUNT_ANSWER": 1,
                "PROCENT": 14.3
              },
              {
                "TEXT": "Wed Jan 10 2024 11:58:00 GMT+0600 (Восточный Казахстан)-Wed Jan 24 2024 11:58:00 GMT+0600 (Восточный Казахстан)",
                "COUNT_ANSWER": 1,
                "PROCENT": 14.3
              },
              {
                "TEXT": "Tue Jan 02 2024 14:36:00 GMT+0600 (Восточный Казахстан)-Tue Jan 16 2024 14:36:00 GMT+0600 (Восточный Казахстан)",
                "COUNT_ANSWER": 1,
                "PROCENT": 14.3
              },
              {
                "TEXT": "Wed Jan 17 2024 16:50:00 GMT+0600 (Восточный Казахстан)-Sat Jan 20 2024 16:50:00 GMT+0600 (Восточный Казахстан)",
                "COUNT_ANSWER": 1,
                "PROCENT": 14.3
              },
              {
                "TEXT": "Wed Jan 31 2024 16:22:00 GMT+0600 (Восточный Казахстан)-Thu Feb 01 2024 16:22:00 GMT+0600 (Восточный Казахстан)",
                "COUNT_ANSWER": 1,
                "PROCENT": 14.3
              }
            ]
          }
        },
        {
          "ID": "1523",
          "UF_ID_RESULT": "479",
          "UF_ID_QUESTION": "90c21656-c81d-47f0-800a-44abfd799418",
          "UF_QUESTION_TYPE": "custom-fields",
          "UF_VARIANT_TYPE": "",
          "UF_ID_PAGE": "264",
          "PARAMS": {
            "NAME": [
              {
                "insert": "Кастомные поля\n"
              }
            ],
            "TYPENAME": "Кастомные поля",
            "GENERAL_RANGE_START": null,
            "GENERAL_RANGE_END": null
          },
          "VARIANTS": [
            {
              "ID": "5436",
              "UF_ID_QUESTION": "1523",
              "UF_ID_VARIANT": "1",
              "UF_VARIANT_VALUE": "текст"
            },
            {
              "ID": "5437",
              "UF_ID_QUESTION": "1523",
              "UF_ID_VARIANT": "60844eea-da56-4ea4-99c8-d943499f8a54",
              "UF_VARIANT_VALUE": "Телефон"
            },
            {
              "ID": "5438",
              "UF_ID_QUESTION": "1523",
              "UF_ID_VARIANT": "8d734349-081f-4284-be52-e372e4c42ab4",
              "UF_VARIANT_VALUE": "email"
            },
            {
              "ID": "5439",
              "UF_ID_QUESTION": "1523",
              "UF_ID_VARIANT": "51a0cfc1-0241-4f67-9215-577227bbf25d",
              "UF_VARIANT_VALUE": "Область текста"
            }
          ],
          "FORMS": [
            [
              {
                "ID": "449",
                "UF_ID_QUESTION": "1523",
                "UF_ID_FIELD": "1",
                "UF_ID_TYPE_FIELD": "text",
                "UF_VALUE_FIELD": "текст",
                "UF_FILED_ANSWER": "12312",
                "UF_FIELD_FILLED": "true"
              },
              {
                "ID": "450",
                "UF_ID_QUESTION": "1523",
                "UF_ID_FIELD": "60844eea-da56-4ea4-99c8-d943499f8a54",
                "UF_ID_TYPE_FIELD": "phone",
                "UF_VALUE_FIELD": "Телефон",
                "UF_FILED_ANSWER": "+7(123)123-12-31",
                "UF_FIELD_FILLED": "true"
              },
              {
                "ID": "451",
                "UF_ID_QUESTION": "1523",
                "UF_ID_FIELD": "8d734349-081f-4284-be52-e372e4c42ab4",
                "UF_ID_TYPE_FIELD": "email",
                "UF_VALUE_FIELD": "email",
                "UF_FILED_ANSWER": "фывфы@mail.ru",
                "UF_FIELD_FILLED": "true"
              },
              {
                "ID": "452",
                "UF_ID_QUESTION": "1523",
                "UF_ID_FIELD": "51a0cfc1-0241-4f67-9215-577227bbf25d",
                "UF_ID_TYPE_FIELD": "textarea",
                "UF_VALUE_FIELD": "Область текста",
                "UF_FILED_ANSWER": "фывфы@mail.ru",
                "UF_FIELD_FILLED": "true"
              }
            ]
          ],
          "ANSWERS": {
            "USER_ANSWER": []
          }
        },
        {
          "ID": "1524",
          "UF_ID_RESULT": "479",
          "UF_ID_QUESTION": "0be8c1c0-7e08-46bc-929c-1d4f382ec74c",
          "UF_QUESTION_TYPE": "custom-fields",
          "UF_VARIANT_TYPE": "",
          "UF_ID_PAGE": "264",
          "PARAMS": {
            "NAME": [
              {
                "insert": "Кастомные поля 2\n"
              }
            ],
            "TYPENAME": "Кастомные поля",
            "GENERAL_RANGE_START": null,
            "GENERAL_RANGE_END": null
          },
          "VARIANTS": [
            {
              "ID": "5440",
              "UF_ID_QUESTION": "1524",
              "UF_ID_VARIANT": "1",
              "UF_VARIANT_VALUE": "Текст 2"
            },
            {
              "ID": "5441",
              "UF_ID_QUESTION": "1524",
              "UF_ID_VARIANT": "78ce0bf9-e1aa-4483-a45a-5c122cbddbb6",
              "UF_VARIANT_VALUE": "Телефон 2"
            },
            {
              "ID": "5442",
              "UF_ID_QUESTION": "1524",
              "UF_ID_VARIANT": "2583bdba-96dd-4da2-ae2b-d4cc40ecd469",
              "UF_VARIANT_VALUE": "Email 2"
            },
            {
              "ID": "5443",
              "UF_ID_QUESTION": "1524",
              "UF_ID_VARIANT": "a088b845-d496-4aad-91b2-d9d461f409ed",
              "UF_VARIANT_VALUE": "Область текста 2"
            }
          ],
          "FORMS": [
            [
              {
                "ID": "453",
                "UF_ID_QUESTION": "1524",
                "UF_ID_FIELD": "1",
                "UF_ID_TYPE_FIELD": "text",
                "UF_VALUE_FIELD": "Текст 2",
                "UF_FILED_ANSWER": "фывфы@mail.ru",
                "UF_FIELD_FILLED": "true"
              },
              {
                "ID": "454",
                "UF_ID_QUESTION": "1524",
                "UF_ID_FIELD": "78ce0bf9-e1aa-4483-a45a-5c122cbddbb6",
                "UF_ID_TYPE_FIELD": "phone",
                "UF_VALUE_FIELD": "Телефон 2",
                "UF_FILED_ANSWER": "+7(123)123-12-31",
                "UF_FIELD_FILLED": "true"
              },
              {
                "ID": "455",
                "UF_ID_QUESTION": "1524",
                "UF_ID_FIELD": "2583bdba-96dd-4da2-ae2b-d4cc40ecd469",
                "UF_ID_TYPE_FIELD": "email",
                "UF_VALUE_FIELD": "Email 2",
                "UF_FILED_ANSWER": "фывфы@mail.ru",
                "UF_FIELD_FILLED": "true"
              },
              {
                "ID": "456",
                "UF_ID_QUESTION": "1524",
                "UF_ID_FIELD": "a088b845-d496-4aad-91b2-d9d461f409ed",
                "UF_ID_TYPE_FIELD": "textarea",
                "UF_VALUE_FIELD": "Область текста 2",
                "UF_FILED_ANSWER": "123123123",
                "UF_FIELD_FILLED": "true"
              }
            ]
          ],
          "ANSWERS": {
            "USER_ANSWER": []
          }
        }
      ],
      [
        {
          "ID": "1525",
          "UF_ID_RESULT": "479",
          "UF_ID_QUESTION": "65989748-d47a-45b9-b32c-b4ae4aaee04e",
          "UF_QUESTION_TYPE": "custom-fields",
          "UF_VARIANT_TYPE": "",
          "UF_ID_PAGE": "265",
          "PARAMS": {
            "NAME": [
              {
                "insert": "Кастомные поля страница 2\n"
              }
            ],
            "TYPENAME": "Кастомные поля",
            "GENERAL_RANGE_START": null,
            "GENERAL_RANGE_END": null
          },
          "VARIANTS": [
            {
              "ID": "5444",
              "UF_ID_QUESTION": "1525",
              "UF_ID_VARIANT": "1",
              "UF_VARIANT_VALUE": "текст"
            },
            {
              "ID": "5445",
              "UF_ID_QUESTION": "1525",
              "UF_ID_VARIANT": "a55a6b48-1a53-44ba-a44d-835f501c6a7b",
              "UF_VARIANT_VALUE": "Телефон"
            }
          ],
          "FORMS": [
            [
              {
                "ID": "457",
                "UF_ID_QUESTION": "1525",
                "UF_ID_FIELD": "1",
                "UF_ID_TYPE_FIELD": "text",
                "UF_VALUE_FIELD": "текст",
                "UF_FILED_ANSWER": "фывфы@mail.ru",
                "UF_FIELD_FILLED": "true"
              },
              {
                "ID": "458",
                "UF_ID_QUESTION": "1525",
                "UF_ID_FIELD": "a55a6b48-1a53-44ba-a44d-835f501c6a7b",
                "UF_ID_TYPE_FIELD": "phone",
                "UF_VALUE_FIELD": "Телефон",
                "UF_FILED_ANSWER": "+7(123)123-12-31",
                "UF_FIELD_FILLED": "true"
              }
            ]
          ],
          "ANSWERS": {
            "USER_ANSWER": []
          }
        },
        {
          "ID": "1526",
          "UF_ID_RESULT": "479",
          "UF_ID_QUESTION": "25d910eb-a8f4-44f8-8faf-7d4e5e49eedd",
          "UF_QUESTION_TYPE": "single-choice",
          "UF_VARIANT_TYPE": "",
          "UF_ID_PAGE": "265",
          "PARAMS": {
            "NAME": [
              {
                "insert": "Одиночный 2\n"
              }
            ],
            "TYPENAME": "Одиночный выбор",
            "GENERAL_RANGE_START": null,
            "GENERAL_RANGE_END": null
          },
          "VARIANTS": [
            {
              "ID": "5446",
              "UF_ID_QUESTION": "1526",
              "UF_ID_VARIANT": "1",
              "UF_VARIANT_VALUE": "Одиночный 2 1"
            },
            {
              "ID": "5447",
              "UF_ID_QUESTION": "1526",
              "UF_ID_VARIANT": "2",
              "UF_VARIANT_VALUE": "Одиночный 2 2"
            }
          ],
          "ANSWERS": {
            "CORRECT_ANSWER": [""],
            "USER_ANSWER": {
              "1": {
                "TEXT": "Одиночный 2 1",
                "COUNT_ANSWER": 4,
                "PROCENT": 57.1
              },
              "2": {
                "TEXT": "Одиночный 2 2",
                "COUNT_ANSWER": 3,
                "PROCENT": 42.9
              }
            }
          }
        }
      ]
    ]
  }
}
